LICENSE.txt
README.md
build.gradle
gradlew
gradlew.bat
requirements.txt
setup.cfg
setup.py
scriptable/__init__.py
scriptable/abstract_engine.py
scriptable/hypothesis_engine.py
scriptable/hypothesis_visitor.py
scriptable/mustache_engine.py
scriptable/mustache_visitor.py
scriptable/typescript_engine.py
scriptable/typescript_visitor.py
scriptable.egg-info/PKG-INFO
scriptable.egg-info/SOURCES.txt
scriptable.egg-info/dependency_links.txt
scriptable.egg-info/requires.txt
scriptable.egg-info/top_level.txt
scriptable/__tests__/hypothesis_engine_test.py
scriptable/__tests__/mustache_engine_test.py
scriptable/__tests__/typescript_engine_test.py
scriptable/antlr/Hypothesis.interp
scriptable/antlr/Hypothesis.tokens
scriptable/antlr/HypothesisLexer.interp
scriptable/antlr/HypothesisLexer.py
scriptable/antlr/HypothesisLexer.tokens
scriptable/antlr/HypothesisListener.py
scriptable/antlr/HypothesisParser.py
scriptable/antlr/HypothesisVisitor.py
scriptable/antlr/MustacheLexer.interp
scriptable/antlr/MustacheLexer.py
scriptable/antlr/MustacheLexer.tokens
scriptable/antlr/MustacheParser.interp
scriptable/antlr/MustacheParser.py
scriptable/antlr/MustacheParser.tokens
scriptable/antlr/MustacheParserListener.py
scriptable/antlr/MustacheParserVisitor.py
scriptable/antlr/Typescript.interp
scriptable/antlr/Typescript.tokens
scriptable/antlr/TypescriptLexer.interp
scriptable/antlr/TypescriptLexer.py
scriptable/antlr/TypescriptLexer.tokens
scriptable/antlr/TypescriptListener.py
scriptable/antlr/TypescriptParser.py
scriptable/antlr/TypescriptVisitor.py
scriptable/antlr/__init__.py
scriptable/api/__init__.py
scriptable/api/accessor.py
scriptable/api/ast.py
scriptable/api/ast_binding.py
scriptable/api/ast_restrictions.py
scriptable/api/exit_value.py
scriptable/api/property_resolver.py
scriptable/ast/Return.py
scriptable/ast/__init__.py
scriptable/ast/boolean.py
scriptable/ast/number.py
scriptable/ast/optional.py
scriptable/ast/type.py
scriptable/ast/control/Break.py
scriptable/ast/control/Continue.py
scriptable/ast/control/For.py
scriptable/ast/control/ForIn.py
scriptable/ast/control/ForOf.py
scriptable/ast/control/While.py
scriptable/ast/control/__init__.py
