Metadata-Version: 2.1
Name: scriptable
Version: 0.1.7
Summary: Scriptable is a sand-boxed scripting engine which can be used safely in an embedded environment.
Home-page: https://github.com/c7nw3r/scriptable
Author: x-and-y
Author-email: christian.weber@leftshift.one
License: Apache Software License
Download-URL: https://github.com/c7nw3r/scriptable/archive/refs/tags/v0.1.7.tar.gz
Keywords: scripting-engine
Platform: UNKNOWN
Classifier: Development Status :: 4 - Beta
Classifier: Intended Audience :: Developers
Classifier: Topic :: Software Development :: Interpreters
Classifier: License :: OSI Approved :: Apache Software License
Classifier: Programming Language :: Python :: 3
Classifier: Programming Language :: Python :: 3.4
Classifier: Programming Language :: Python :: 3.5
Classifier: Programming Language :: Python :: 3.6
